.history_payload/blob_store/bcc5a585fa5194627212146eebbecb64_snn_tff_neuron.v
`timescale 1ns / 1ps

// Hardware-Efficient Leaky Integrate-and-Fire (LIF) Neuron
// Uses a bit-shift leak to avoid DSP multipliers.
//
// Equation: U[t] = U[t-1] - (U[t-1] >> LEAK_SHIFT) + I[t]
// If U[t] >= THRESHOLD, Spike = 1 and U[t] = 0.

module snn_tff_neuron #(
    parameter DATA_WIDTH = 16,
    parameter LEAK_SHIFT = 3,       // alpha approx 0.875
    parameter THRESHOLD  = 16'd500  // Firing threshold
) (
    input  wire                   clk,
    input  wire                   rst,
    
    input  wire signed [DATA_WIDTH-1:0] syn_current, // I[t]
    input  wire                   valid_in,
    
    output reg                    spike_out,
    output reg                    valid_out
);

    reg signed [DATA_WIDTH-1:0] membrane_u;
    
    wire signed [DATA_WIDTH-1:0] leak_amount = membrane_u >>> LEAK_SHIFT;
    wire signed [DATA_WIDTH-1:0] u_decayed   = membrane_u - leak_amount;
    wire signed [DATA_WIDTH-1:0] u_temp      = u_decayed + syn_current;

    always @(posedge clk) begin
        if (rst) begin
            membrane_u <= 0;
            spike_out  <= 0;
            valid_out  <= 0;
        end else begin
            valid_out <= valid_in;
            
            if (valid_in) begin
                if (u_temp >= THRESHOLD) begin
                    spike_out  <= 1'b1;
                    membrane_u <= 0; // Hard reset to resting potential (0)
                end else begin
                    spike_out  <= 1'b0;
                    membrane_u <= u_temp;
                end
            end else begin
                spike_out <= 1'b0;
                // Leak still happens even if no new valid synaptic current? 
                // Usually for clock-driven SNNs, valid_in serves as a clock tick for the SNN layer.
                // If valid_in is 0, the SNN is paused.
            end
        end
    end

endmodule

.history_payload/flattened/ev14/rtl/snn_tff_layer.v
`timescale 1ns / 1ps

// Spike-Based Traffic Filter Firewall (SNN-TFF)
// Prototype Fully Connected Spiking Layer (8 inputs -> 2 outputs)

module snn_tff_layer (
    input  wire         clk,
    input  wire         rst,
    
    input  wire [7:0]   in_spikes,
    input  wire         valid_in,
    
    output wire [1:0]   out_spikes,
    output wire         valid_out
);

    // Hardcoded weights for the prototype to avoid complex BRAM fetching
    // Weights are signed 16-bit integers
    // Neuron 0 (Safe Predictor): Excited by regular traffic features (e.g. port 80, standard length)
    wire signed [15:0] w0 [0:7];
    assign w0[0] = 16'd50;
    assign w0[1] = 16'd20;
    assign w0[2] = 16'd0;
    assign w0[3] = 16'd10;
    assign w0[4] = -16'd100; // Penalize anomaly feature
    assign w0[5] = -16'd50;
    assign w0[6] = 16'd30;
    assign w0[7] = 16'd40;

    // Neuron 1 (Anomaly Predictor): Excited by malicious features (e.g. rapid SYN, strange ports, fragmentation)
    wire signed [15:0] w1 [0:7];
    assign w1[0] = -16'd40;
    assign w1[1] = -16'd20;
    assign w1[2] = 16'd150; // Highly excited by anomaly feature 2
    assign w1[3] = 16'd80;
    assign w1[4] = 16'd120;
    assign w1[5] = 16'd60;
    assign w1[6] = -16'd30;
    assign w1[7] = 16'd50;

    // Combinatorial Synaptic Integration (Dot Product of Spikes * Weights)
    // Since inputs are binary spikes, this is just a conditional adder tree!
    reg signed [15:0] current_n0;
    reg signed [15:0] current_n1;
    
    integer i;
    always @(*) begin
        current_n0 = 0;
        current_n1 = 0;
        for (i = 0; i < 8; i = i + 1) begin
            if (in_spikes[i]) begin
                current_n0 = current_n0 + w0[i];
                current_n1 = current_n1 + w1[i];
            end
        end
    end

    // Pipeline stage for Synaptic Integration to meet timing
    reg signed [15:0] current_n0_reg;
    reg signed [15:0] current_n1_reg;
    reg               valid_reg;

    always @(posedge clk) begin
        if (rst) begin
            current_n0_reg <= 0;
            current_n1_reg <= 0;
            valid_reg      <= 0;
        end else begin
            valid_reg <= valid_in;
            if (valid_in) begin
                current_n0_reg <= current_n0;
                current_n1_reg <= current_n1;
            end
        end
    end

    // Instantiate LIF Neurons
    wire valid_n0, valid_n1;
    
    snn_tff_neuron #(
        .DATA_WIDTH(16),
        .LEAK_SHIFT(3),      // Alpha ~0.875
        .THRESHOLD(16'd300)  // Needs a few spikes to fire
    ) neuron_safe (
        .clk(clk),
        .rst(rst),
        .syn_current(current_n0_reg),
        .valid_in(valid_reg),
        .spike_out(out_spikes[0]),
        .valid_out(valid_n0)
    );

    snn_tff_neuron #(
        .DATA_WIDTH(16),
        .LEAK_SHIFT(3),
        .THRESHOLD(16'd300)
    ) neuron_anomaly (
        .clk(clk),
        .rst(rst),
        .syn_current(current_n1_reg),
        .valid_in(valid_reg),
        .spike_out(out_spikes[1]),
        .valid_out(valid_n1)
    );
    
    assign valid_out = valid_n0; // Both neurons share the same pipeline depth

endmodule

.history_payload/flattened/ev14/tb/tb_snn_layer.v
`timescale 1ns / 1ps

module tb_snn_layer;

    reg clk;
    reg rst;
    
    reg [7:0] in_spikes;
    reg       valid_in;
    
    wire [1:0] out_spikes;
    wire       valid_out;

    snn_tff_layer uut (
        .clk(clk),
        .rst(rst),
        .in_spikes(in_spikes),
        .valid_in(valid_in),
        .out_spikes(out_spikes),
        .valid_out(valid_out)
    );

    initial begin
        $dumpfile("tb_snn_layer.vcd");
        $dumpvars(0, tb_snn_layer);
        clk = 0;
        forever #3.2 clk = ~clk; // 156.25 MHz
    end
    
    always @(posedge clk) begin
        if (valid_out) begin
            if (out_spikes[0]) $display("[%0t] SNN FIRED: Safe Traffic Detected", $time);
            if (out_spikes[1]) $display("[%0t] SNN FIRED: Anomaly/Threat Detected (DROP)", $time);
        end
    end

    // Helper task to inject a spike train over N cycles
    task inject_spikes(input [7:0] pattern, input integer cycles);
        integer i;
        begin
            for (i=0; i<cycles; i=i+1) begin
                @(posedge clk);
                valid_in <= 1;
                in_spikes <= pattern;
            end
            @(posedge clk);
            valid_in <= 0;
            in_spikes <= 0;
        end
    endtask

    initial begin
        rst = 1;
        valid_in = 0;
        in_spikes = 0;
        
        #100;
        rst = 0;
        #20;
        
        $display("[%0t] Experiment 1: Normal Traffic Pattern (Excites Safe Neuron)", $time);
        // Pattern with bits 0, 1, 6, 7 active (strong weights for N0)
        inject_spikes(8'b11000011, 8); // 8 consecutive cycles
        
        #100;
        
        $display("[%0t] Experiment 2: Anomaly Traffic Pattern (Excites Anomaly Neuron)", $time);
        // Pattern with bits 2, 3, 4, 5 active (strong weights for N1)
        inject_spikes(8'b00111100, 10);
        
        #100;
        
        $display("[%0t] Experiment 3: Low-rate Anomaly (Should leak and not fire)", $time);
        // Pattern with bits 2, 3, 4 active, but interleaved with zeros to test the LEAK function.
        // If we inject sparsely, the leak should prevent firing.
        inject_spikes(8'b00011100, 1);
        #30; // Wait and leak
        inject_spikes(8'b00011100, 1);
        #30;
        inject_spikes(8'b00011100, 1);
        #30;
        inject_spikes(8'b00011100, 1);
        
        #200;
        $finish;
    end

endmodule

.history_payload/blob_store/8ffc3333491a554eccf8876dc2f261e1_tb_snn_layer.vcd
$date
	Fri Jun 26 17:32:34 2026
$end
$version
	Icarus Verilog
$end
$timescale
	1ps
$end
$scope module tb_snn_layer $end
$var wire 1 ! valid_out $end
$var wire 2 " out_spikes [1:0] $end
$var reg 1 # clk $end
$var reg 8 $ in_spikes [7:0] $end
$var reg 1 % rst $end
$var reg 1 & valid_in $end
$scope module uut $end
$var wire 1 # clk $end
$var wire 8 ' in_spikes [7:0] $end
$var wire 1 % rst $end
$var wire 1 & valid_in $end
$var wire 1 ! valid_out $end
$var wire 1 ( valid_n1 $end
$var wire 1 ) valid_n0 $end
$var wire 2 * out_spikes [1:0] $end
$var reg 16 + current_n0 [15:0] $end
$var reg 16 , current_n0_reg [15:0] $end
$var reg 16 - current_n1 [15:0] $end
$var reg 16 . current_n1_reg [15:0] $end
$var reg 1 / valid_reg $end
$var integer 32 0 i [31:0] $end
$scope module neuron_anomaly $end
$var wire 1 # clk $end
$var wire 1 % rst $end
$var wire 16 1 syn_current [15:0] $end
$var wire 1 / valid_in $end
$var wire 16 2 u_temp [15:0] $end
$var wire 16 3 u_decayed [15:0] $end
$var wire 16 4 leak_amount [15:0] $end
$var parameter 32 5 DATA_WIDTH $end
$var parameter 32 6 LEAK_SHIFT $end
$var parameter 16 7 THRESHOLD $end
$var reg 16 8 membrane_u [15:0] $end
$var reg 1 9 spike_out $end
$var reg 1 ( valid_out $end
$upscope $end
$scope module neuron_safe $end
$var wire 1 # clk $end
$var wire 1 % rst $end
$var wire 16 : syn_current [15:0] $end
$var wire 1 / valid_in $end
$var wire 16 ; u_temp [15:0] $end
$var wire 16 < u_decayed [15:0] $end
$var wire 16 = leak_amount [15:0] $end
$var parameter 32 > DATA_WIDTH $end
$var parameter 32 ? LEAK_SHIFT $end
$var parameter 16 @ THRESHOLD $end
$var reg 16 A membrane_u [15:0] $end
$var reg 1 B spike_out $end
$var reg 1 ) valid_out $end
$upscope $end
$upscope $end
$scope task inject_spikes $end
$var reg 8 C pattern [7:0] $end
$var integer 32 D cycles [31:0] $end
$var integer 32 E i [31:0] $end
$upscope $end
$upscope $end
$enddefinitions $end
$comment Show the parameter values. $end
$dumpall
b100101100 @
b11 ?
b10000 >
b100101100 7
b11 6
b10000 5
$end
#0
$dumpvars
bx E
bx D
bx C
xB
bx A
bx =
bx <
bx ;
bx :
x9
bx 8
bx 4
bx 3
bx 2
bx 1
b1000 0
x/
bx .
b0 -
bx ,
b0 +
bx *
x)
x(
b0 '
0&
1%
b0 $
0#
bx "
x!
$end
#3200
b0 ;
b0 <
b0 =
b0 2
b0 3
b0 4
0!
0)
0B
b0 A
0(
b0 "
b0 *
09
b0 8
0/
b0 .
b0 1
b0 ,
b0 :
1#
#6400
0#
#9600
1#
#12800
0#
#16000
1#
#19200
0#
#22400
1#
#25600
0#
#28800
1#
#32000
0#
#35200
1#
#38400
0#
#41600
1#
#44800
0#
#48000
1#
#51200
0#
#54400
1#
#57600
0#
#60800
1#
#64000
0#
#67200
1#
#70400
0#
#73600
1#
#76800
0#
#80000
1#
#83200
0#
#86400
1#
#89600
0#
#92800
1#
#96000
0#
#99200
1#
#100000
0%
#102400
0#
#105600
1#
#108800
0#
#112000
1#
#115200
0#
#118400
1#
#120000
b0 E
b1000 D
b11000011 C
#121600
0#
#124800
b1111111111011000 -
b10001100 +
b1000 0
b11000011 $
b11000011 '
1&
b1 E
1#
#128000
0#
#131200
b1111111111011000 2
b1111111111011000 .
b1111111111011000 1
b10001100 ;
b10001100 ,
b10001100 :
1/
b10 E
1#
#134400
0#
#137600
b10001 =
b10 "
b10 *
19
1(
b100000111 ;
b1111011 <
b10001100 A
1!
1)
b11 E
1#
#140800
0#
#144000
b100000 =
b101110011 ;
b11100111 <
b100000111 A
b100 E
1#
#147200
0#
#150400
b0 =
b10001100 ;
b0 <
b0 A
b11 "
b11 *
1B
b101 E
1#
#153600
0#
#156800
b10001 =
b100000111 ;
b1111011 <
b10001100 A
b10 "
b10 *
0B
b110 E
1#
#160000
0#
#163200
b100000 =
b101110011 ;
b11100111 <
b100000111 A
b111 E
1#
#166400
0#
#169600
b0 =
b10001100 ;
b0 <
b0 A
b11 "
b11 *
1B
b1000 E
1#
#172800
0#
#176000
b10001 =
b1000 0
b0 -
b0 +
b100000111 ;
b1111011 <
b10001100 A
b10 "
b10 *
0B
b0 $
b0 '
0&
1#
#179200
0#
#182400
b100000 =
b101110011 ;
b11100111 <
b100000111 A
0/
1#
#185600
0#
#188800
b0 "
b0 *
09
0(
0!
0)
1#
#192000
0#
#195200
1#
#198400
0#
#201600
1#
#204800
0#
#208000
1#
#211200
0#
#214400
1#
#217600
0#
#220800
1#
#224000
0#
#227200
1#
#230400
0#
#233600
1#
#236800
0#
#240000
1#
#243200
0#
#246400
1#
#249600
0#
#252800
1#
#256000
0#
#259200
1#
#262400
0#
#265600
1#
#268800
0#
#272000
1#
#275200
0#
#276000
b0 E
b1010 D
b111100 C
#278400
b1111111101110100 +
b110011010 -
b1000 0
b111100 $
b111100 '
1&
b1 E
1#
#281600
0#
#284800
b110011010 2
b110011010 .
b110011010 1
b1011011 ;
b1111111101110100 ,
b1111111101110100 :
1/
b10 E
1#
#288000
0#
#291200
b1011 =
b10 "
b10 *
19
1(
b1111111111000100 ;
b1010000 <
b1011011 A
1!
1)
b11 E
1#
#294400
0#
#297600
b0 =
b1111111101110100 ;
b0 <
b0 A
b11 "
b11 *
1B
b100 E
1#
#300800
0#
#304000
b101 E
1#
#307200
0#
#310400
b110 E
1#
#313600
0#
#316800
b111 E
1#
#320000
0#
#323200
b1000 E
1#
#326400
0#
#329600
b1001 E
1#
#332800
0#
#336000
b1010 E
1#
#339200
0#
#342400
b1000 0
b0 -
b0 +
b0 $
b0 '
0&
1#
#345600
0#
#348800
0/
1#
#352000
0#
#355200
09
0(
b0 "
b0 *
0B
0!
0)
1#
#358400
0#
#361600
1#
#364800
0#
#368000
1#
#371200
0#
#374400
1#
#377600
0#
#380800
1#
#384000
0#
#387200
1#
#390400
0#
#393600
1#
#396800
0#
#400000
1#
#403200
0#
#406400
1#
#409600
0#
#412800
1#
#416000
0#
#419200
1#
#422400
0#
#425600
1#
#428800
0#
#432000
1#
#435200
0#
#438400
1#
#441600
0#
#442400
b0 E
b1 D
b11100 C
#444800
b1111111110100110 +
b101011110 -
b1000 0
b11100 $
b11100 '
1&
b1 E
1#
#448000
0#
#451200
b1000 0
b0 -
b0 +
b0 $
b0 '
0&
b101011110 2
b101011110 .
b101011110 1
b1111111110100110 ;
b1111111110100110 ,
b1111111110100110 :
1/
1#
#454400
0#
#457600
0/
19
1(
b11 "
b11 *
1B
1!
1)
1#
#460800
0#
#464000
0B
0!
0)
b0 "
b0 *
09
0(
1#
#467200
0#
#470400
1#
#473600
0#
#476800
1#
#480000
0#
#481200
b0 E
#483200
b1111111110100110 +
b101011110 -
b1000 0
b11100 $
b11100 '
1&
b1 E
1#
#486400
0#
#489600
b1000 0
b0 -
b0 +
b0 $
b0 '
0&
1/
1#
#492800
0#
#496000
0/
19
1(
b11 "
b11 *
1B
1!
1)
1#
#499200
0#
#502400
0B
0!
0)
b0 "
b0 *
09
0(
1#
#505600
0#
#508800
1#
#512000
0#
#515200
1#
#518400
0#
#519600
b0 E
#521600
b1111111110100110 +
b101011110 -
b1000 0
b11100 $
b11100 '
1&
b1 E
1#
#524800
0#
#528000
b1000 0
b0 -
b0 +
b0 $
b0 '
0&
1/
1#
#531200
0#
#534400
0/
19
1(
b11 "
b11 *
1B
1!
1)
1#
#537600
0#
#540800
0B
0!
0)
b0 "
b0 *
09
0(
1#
#544000
0#
#547200
1#
#550400
0#
#553600
1#
#556800
0#
#558000
b0 E
#560000
b1111111110100110 +
b101011110 -
b1000 0
b11100 $
b11100 '
1&
b1 E
1#
#563200
0#
#566400
b1000 0
b0 -
b0 +
b0 $
b0 '
0&
1/
1#
#569600
0#
#572800
0/
19
1(
b11 "
b11 *
1B
1!
1)
1#
#576000
0#
#579200
0B
0!
0)
b0 "
b0 *
09
0(
1#
