.history_payload/Master_Archive/Engineering_History/05_RTL/rtl_v001/ha_tff_parser_v001.v
`timescale 1ns / 1ps

module ha_tff_parser_v001 (
    input  wire        clk,
    input  wire        rst,
    
    // AXI4-Stream Sink Interface
    input  wire [7:0]  s_axis_tdata,
    input  wire        s_axis_tvalid,
    input  wire        s_axis_tlast,
    output wire        s_axis_tready,
    
    // Extracted 5-tuple output
    output reg  [31:0] src_ip,
    output reg  [31:0] dst_ip,
    output reg  [15:0] src_port,
    output reg  [15:0] dst_port,
    output reg  [7:0]  protocol,
    output reg         tuple_valid,
    output reg         parse_error
);

    // We can always consume data in this simple model
    assign s_axis_tready = 1'b1;

    localparam STATE_IDLE  = 2'd0;
    localparam STATE_PARSE = 2'd1;
    localparam STATE_DROP  = 2'd2;

    reg [1:0]  state;
    reg [15:0] byte_cnt;
    
    reg [15:0] ethertype;

    always @(posedge clk) begin
        if (rst) begin
            state       <= STATE_IDLE;
            byte_cnt    <= 0;
            tuple_valid <= 0;
            parse_error <= 0;
            src_ip      <= 0;
            dst_ip      <= 0;
            src_port    <= 0;
            dst_port    <= 0;
            protocol    <= 0;
            ethertype   <= 0;
        end else begin
            tuple_valid <= 0; // Default to 0
            
            case (state)
                STATE_IDLE: begin
                    byte_cnt <= 0;
                    parse_error <= 0;
                    if (s_axis_tvalid) begin
                        state <= STATE_PARSE;
                        byte_cnt <= 1;
                    end
                end
                
                STATE_PARSE: begin
                    if (s_axis_tvalid) begin
                        byte_cnt <= byte_cnt + 1;
                        
                        case (byte_cnt)
                            12: ethertype[15:8] <= s_axis_tdata;
                            13: ethertype[7:0]  <= s_axis_tdata;
                            23: protocol        <= s_axis_tdata;
                            
                            26: src_ip[31:24] <= s_axis_tdata;
                            27: src_ip[23:16] <= s_axis_tdata;
                            28: src_ip[15:8]  <= s_axis_tdata;
                            29: src_ip[7:0]   <= s_axis_tdata;
                            
                            30: dst_ip[31:24] <= s_axis_tdata;
                            31: dst_ip[23:16] <= s_axis_tdata;
                            32: dst_ip[15:8]  <= s_axis_tdata;
                            33: dst_ip[7:0]   <= s_axis_tdata;
                            
                            34: src_port[15:8] <= s_axis_tdata;
                            35: src_port[7:0]  <= s_axis_tdata;
                            
                            36: dst_port[15:8] <= s_axis_tdata;
                            37: begin
                                dst_port[7:0] <= s_axis_tdata;
                                // Verify constraints before asserting valid
                                if (ethertype == 16'h0800 && (protocol == 8'h11 || protocol == 8'h06)) begin
                                    tuple_valid <= 1;
                                end else begin
                                    parse_error <= 1;
                                end
                            end
                        endcase
                        
                        if (s_axis_tlast) begin
                            state <= STATE_IDLE;
                        end
                    end
                end
                
                STATE_DROP: begin
                    if (s_axis_tvalid && s_axis_tlast) begin
                        state <= STATE_IDLE;
                    end
                end
                
                default: state <= STATE_IDLE;
            endcase
        end
    end

endmodule

.history_payload/flattened/ev00/tb/tb_ha_tff_parser_v001.v
`timescale 1ns / 1ps

module tb_ha_tff_parser_v001;

    reg clk;
    reg rst;
    
    reg [7:0] s_axis_tdata;
    reg s_axis_tvalid;
    reg s_axis_tlast;
    wire s_axis_tready;
    
    wire [31:0] src_ip;
    wire [31:0] dst_ip;
    wire [15:0] src_port;
    wire [15:0] dst_port;
    wire [7:0]  protocol;
    wire tuple_valid;
    wire parse_error;

    ha_tff_parser_v001 uut (
        .clk(clk),
        .rst(rst),
        .s_axis_tdata(s_axis_tdata),
        .s_axis_tvalid(s_axis_tvalid),
        .s_axis_tlast(s_axis_tlast),
        .s_axis_tready(s_axis_tready),
        .src_ip(src_ip),
        .dst_ip(dst_ip),
        .src_port(src_port),
        .dst_port(dst_port),
        .protocol(protocol),
        .tuple_valid(tuple_valid),
        .parse_error(parse_error)
    );

    initial begin
        $dumpfile("tb_ha_tff_parser_v001.vcd");
        $dumpvars(0, tb_ha_tff_parser_v001);
        clk = 0;
        forever #5 clk = ~clk; // 100 MHz
    end

    // Concurrent checker
    reg success_flag;
    initial success_flag = 0;

    always @(posedge clk) begin
        if (tuple_valid) begin
            success_flag <= 1;
            $display("[%0t] SUCCESS: Tuple Valid asserted!", $time);
            $display("Src IP: %h, Dst IP: %h", src_ip, dst_ip);
            $display("Src Port: %h, Dst Port: %h, Proto: %h", src_port, dst_port, protocol);
        end
        if (parse_error) begin
            $display("[%0t] ERROR: Parse Error asserted!", $time);
        end
    end

    // Helper task to send a byte
    task send_byte(input [7:0] data, input is_last);
        begin
            @(posedge clk);
            s_axis_tvalid <= 1;
            s_axis_tdata <= data;
            s_axis_tlast <= is_last;
        end
    endtask

    integer i;

    initial begin
        rst = 1;
        s_axis_tvalid = 0;
        s_axis_tdata = 0;
        s_axis_tlast = 0;
        
        #100;
        rst = 0;
        #20;
        
        $display("[%0t] Sending Valid UDP Packet...", $time);
        
        // Byte 0-5: Dst MAC
        for (i=0; i<6; i=i+1) send_byte(8'hFF, 0);
        // Byte 6-11: Src MAC
        for (i=0; i<6; i=i+1) send_byte(8'hEE, 0);
        // Byte 12-13: EtherType (IPv4 = 0800)
        send_byte(8'h08, 0); send_byte(8'h00, 0);
        
        // Byte 14: Version/IHL (0x45)
        send_byte(8'h45, 0);
        // Byte 15: TOS
        send_byte(8'h00, 0);
        // Byte 16-17: Total Length
        send_byte(8'h00, 0); send_byte(8'h28, 0);
        // Byte 18-19: Identification
        send_byte(8'hAB, 0); send_byte(8'hCD, 0);
        // Byte 20-21: Flags/Offset
        send_byte(8'h40, 0); send_byte(8'h00, 0);
        // Byte 22: TTL
        send_byte(8'h40, 0);
        // Byte 23: Protocol (UDP = 0x11)
        send_byte(8'h11, 0);
        // Byte 24-25: Header Checksum
        send_byte(8'h00, 0); send_byte(8'h00, 0);
        
        // Byte 26-29: Src IP (192.168.1.100 -> C0 A8 01 64)
        send_byte(8'hC0, 0); send_byte(8'hA8, 0); send_byte(8'h01, 0); send_byte(8'h64, 0);
        // Byte 30-33: Dst IP (10.0.0.5 -> 0A 00 00 05)
        send_byte(8'h0A, 0); send_byte(8'h00, 0); send_byte(8'h00, 0); send_byte(8'h05, 0);
        
        // Byte 34-35: Src Port (1234 -> 04 D2)
        send_byte(8'h04, 0); send_byte(8'hD2, 0);
        // Byte 36-37: Dst Port (80 -> 00 50)
        send_byte(8'h00, 0); send_byte(8'h50, 0);
        
        // Byte 38-41: UDP Length & Checksum
        send_byte(8'h00, 0); send_byte(8'h08, 0);
        send_byte(8'h00, 0); send_byte(8'h00, 0);
        
        // Payload
        send_byte(8'hDE, 0);
        send_byte(8'hAD, 0);
        send_byte(8'hBE, 0);
        send_byte(8'hEF, 1); // tlast = 1
        
        @(posedge clk);
        s_axis_tvalid <= 0;
        s_axis_tlast <= 0;
        
        #100;
        
        if (!success_flag) begin
            $display("[%0t] ERROR: Test Finished but tuple_valid was never asserted!", $time);
        end
        
        #10;
        $finish;
    end

endmodule

.history_payload/blob_store/bf750cfe536859b0742449cc2c2289c4_tb_ha_tff_parser_v001.vcd
$date
	Fri Jun 26 16:56:53 2026
$end
$version
	Icarus Verilog
$end
$timescale
	1ps
$end
$scope module tb_ha_tff_parser_v001 $end
$var wire 1 ! s_axis_tready $end
$var wire 1 " tuple_valid $end
$var wire 16 # src_port [15:0] $end
$var wire 32 $ src_ip [31:0] $end
$var wire 8 % protocol [7:0] $end
$var wire 1 & parse_error $end
$var wire 16 ' dst_port [15:0] $end
$var wire 32 ( dst_ip [31:0] $end
$var reg 1 ) clk $end
$var reg 1 * rst $end
$var reg 8 + s_axis_tdata [7:0] $end
$var reg 1 , s_axis_tlast $end
$var reg 1 - s_axis_tvalid $end
$var reg 1 . success_flag $end
$var integer 32 / i [31:0] $end
$scope module uut $end
$var wire 1 ) clk $end
$var wire 1 * rst $end
$var wire 8 0 s_axis_tdata [7:0] $end
$var wire 1 , s_axis_tlast $end
$var wire 1 ! s_axis_tready $end
$var wire 1 - s_axis_tvalid $end
$var parameter 2 1 STATE_DROP $end
$var parameter 2 2 STATE_IDLE $end
$var parameter 2 3 STATE_PARSE $end
$var reg 16 4 byte_cnt [15:0] $end
$var reg 32 5 dst_ip [31:0] $end
$var reg 16 6 dst_port [15:0] $end
$var reg 16 7 ethertype [15:0] $end
$var reg 1 & parse_error $end
$var reg 8 8 protocol [7:0] $end
$var reg 32 9 src_ip [31:0] $end
$var reg 16 : src_port [15:0] $end
$var reg 2 ; state [1:0] $end
$var reg 1 " tuple_valid $end
$upscope $end
$scope task send_byte $end
$var reg 8 < data [7:0] $end
$var reg 1 = is_last $end
$upscope $end
$upscope $end
$enddefinitions $end
$comment Show the parameter values. $end
$dumpall
b1 3
b0 2
b10 1
$end
#0
$dumpvars
x=
bx <
bx ;
bx :
bx 9
bx 8
bx 7
bx 6
bx 5
bx 4
b0 0
bx /
0.
0-
0,
b0 +
1*
0)
bx (
bx '
x&
bx %
bx $
bx #
x"
1!
$end
#5000
b0 7
b0 %
b0 8
b0 '
b0 6
b0 #
b0 :
b0 (
b0 5
b0 $
b0 9
0&
0"
b0 4
b0 ;
1)
#10000
0)
#15000
1)
#20000
0)
#25000
1)
#30000
0)
#35000
1)
#40000
0)
#45000
1)
#50000
0)
#55000
1)
#60000
0)
#65000
1)
#70000
0)
#75000
1)
#80000
0)
#85000
1)
#90000
0)
#95000
1)
#100000
0)
0*
#105000
1)
#110000
0)
#115000
1)
#120000
0)
0=
b11111111 <
b0 /
#125000
b11111111 +
b11111111 0
1-
b1 /
1)
#130000
0)
#135000
b1 4
b1 ;
b10 /
1)
#140000
0)
#145000
b10 4
b11 /
1)
#150000
0)
#155000
b11 4
b100 /
1)
#160000
0)
#165000
b100 4
b101 /
1)
#170000
0)
#175000
b101 4
b11101110 <
b0 /
1)
#180000
0)
#185000
b110 4
b11101110 +
b11101110 0
b1 /
1)
#190000
0)
#195000
b111 4
b10 /
1)
#200000
0)
#205000
b1000 4
b11 /
1)
#210000
0)
#215000
b1001 4
b100 /
1)
#220000
0)
#225000
b1010 4
b101 /
1)
#230000
0)
#235000
b1011 4
b1000 <
b110 /
1)
#240000
0)
#245000
b1100 4
b1000 +
b1000 0
b0 <
1)
#250000
0)
#255000
b100000000000 7
b1101 4
b0 +
b0 0
b1000101 <
1)
#260000
0)
#265000
b1110 4
b1000101 +
b1000101 0
b0 <
1)
#270000
0)
#275000
b1111 4
b0 +
b0 0
1)
#280000
0)
#285000
b10000 4
b101000 <
1)
#290000
0)
#295000
b10001 4
b101000 +
b101000 0
b10101011 <
1)
#300000
0)
#305000
b10010 4
b10101011 +
b10101011 0
b11001101 <
1)
#310000
0)
#315000
b10011 4
b11001101 +
b11001101 0
b1000000 <
1)
#320000
0)
#325000
b10100 4
b1000000 +
b1000000 0
b0 <
1)
#330000
0)
#335000
b10101 4
b0 +
b0 0
b1000000 <
1)
#340000
0)
#345000
b10110 4
b1000000 +
b1000000 0
b10001 <
1)
#350000
0)
#355000
b10111 4
b10001 +
b10001 0
b0 <
1)
#360000
0)
#365000
b10001 %
b10001 8
b11000 4
b0 +
b0 0
1)
#370000
0)
#375000
b11001 4
b11000000 <
1)
#380000
0)
#385000
b11010 4
b11000000 +
b11000000 0
b10101000 <
1)
#390000
0)
#395000
b11000000000000000000000000000000 $
b11000000000000000000000000000000 9
b11011 4
b10101000 +
b10101000 0
b1 <
1)
#400000
0)
#405000
b11000000101010000000000000000000 $
b11000000101010000000000000000000 9
b11100 4
b1 +
b1 0
b1100100 <
1)
#410000
0)
#415000
b11000000101010000000000100000000 $
b11000000101010000000000100000000 9
b11101 4
b1100100 +
b1100100 0
b1010 <
1)
#420000
0)
#425000
b11000000101010000000000101100100 $
b11000000101010000000000101100100 9
b11110 4
b1010 +
b1010 0
b0 <
1)
#430000
0)
#435000
b1010000000000000000000000000 (
b1010000000000000000000000000 5
b11111 4
b0 +
b0 0
1)
#440000
0)
#445000
b100000 4
b101 <
1)
#450000
0)
#455000
b100001 4
b101 +
b101 0
b100 <
1)
#460000
0)
#465000
b1010000000000000000000000101 (
b1010000000000000000000000101 5
b100010 4
b100 +
b100 0
b11010010 <
1)
#470000
0)
#475000
b10000000000 #
b10000000000 :
b100011 4
b11010010 +
b11010010 0
b0 <
1)
#480000
0)
#485000
b10011010010 #
b10011010010 :
b100100 4
b0 +
b0 0
b1010000 <
1)
#490000
0)
#495000
b100101 4
b1010000 +
b1010000 0
b0 <
1)
#500000
0)
#505000
1"
b1010000 '
b1010000 6
b100110 4
b0 +
b0 0
b1000 <
1)
#510000
0)
#515000
1.
b100111 4
0"
b1000 +
b1000 0
b0 <
1)
#520000
0)
#525000
b101000 4
b0 +
b0 0
1)
#530000
0)
#535000
b101001 4
b11011110 <
1)
#540000
0)
#545000
b101010 4
b11011110 +
b11011110 0
b10101101 <
1)
#550000
0)
#555000
b101011 4
b10101101 +
b10101101 0
b10111110 <
1)
#560000
0)
#565000
b101100 4
b10111110 +
b10111110 0
1=
b11101111 <
1)
#570000
0)
#575000
b101101 4
1,
b11101111 +
b11101111 0
1)
#580000
0)
#585000
b0 ;
b101110 4
0,
0-
1)
#590000
0)
#595000
b0 4
1)
