.history_payload/flattened/ev17/rtl/snn_tff_neuron_v003.v
`timescale 1ns / 1ps

// Hardware-Efficient Leaky Integrate-and-Fire (LIF) Neuron (v003)
// BUG-004 Fix: Parameter THRESHOLD must be signed to prevent unsigned cast of negative potentials.

module snn_tff_neuron_v003 #(
    parameter DATA_WIDTH = 16,
    parameter LEAK_SHIFT = 3,       
    parameter signed [15:0] THRESHOLD  = 16'sd1000  // Increased threshold to test temporal integration
) (
    input  wire                   clk,
    input  wire                   rst,
    
    input  wire signed [DATA_WIDTH-1:0] syn_current, // I[t]
    input  wire                   valid_in,
    
    output reg                    spike_out
);

    reg signed [DATA_WIDTH-1:0] membrane_u;
    
    wire signed [DATA_WIDTH-1:0] leak_amount = membrane_u >>> LEAK_SHIFT;
    wire signed [DATA_WIDTH-1:0] u_decayed   = membrane_u - leak_amount;
    
    wire signed [DATA_WIDTH-1:0] syn_input   = valid_in ? syn_current : 0;
    wire signed [DATA_WIDTH-1:0] u_temp      = u_decayed + syn_input;

    always @(posedge clk) begin
        if (rst) begin
            membrane_u <= 0;
            spike_out  <= 0;
        end else begin
            // Explicit signed comparison
            if (u_temp >= THRESHOLD) begin
                spike_out  <= 1'b1;
                membrane_u <= 0; // Hard reset to resting potential (0)
            end else begin
                spike_out  <= 1'b0;
                // Prevent negative divergence (floor at resting potential -1000 roughly)
                if (u_temp < -16'sd2000) begin
                    membrane_u <= -16'sd2000;
                end else begin
                    membrane_u <= u_temp;
                end
            end
        end
    end

endmodule

.history_payload/flattened/ev17/rtl/snn_tff_layer_v003.v
`timescale 1ns / 1ps

// Spike-Based Traffic Filter Firewall (SNN-TFF) v003
// Prototype Fully Connected Spiking Layer (8 inputs -> 2 outputs)
// Fixes BUG-004

module snn_tff_layer_v003 (
    input  wire         clk,
    input  wire         rst,
    
    input  wire [7:0]   in_spikes,
    input  wire         valid_in,
    
    output wire [1:0]   out_spikes,
    output reg          valid_out
);

    wire signed [15:0] w0 [0:7];
    assign w0[0] = 16'sd50;
    assign w0[1] = 16'sd20;
    assign w0[2] = 16'sd0;
    assign w0[3] = 16'sd10;
    assign w0[4] = -16'sd100; 
    assign w0[5] = -16'sd50;
    assign w0[6] = 16'sd30;
    assign w0[7] = 16'sd40;

    wire signed [15:0] w1 [0:7];
    assign w1[0] = -16'sd40;
    assign w1[1] = -16'sd20;
    assign w1[2] = 16'sd150; 
    assign w1[3] = 16'sd80;
    assign w1[4] = 16'sd120;
    assign w1[5] = 16'sd60;
    assign w1[6] = -16'sd30;
    assign w1[7] = 16'sd50;

    reg signed [15:0] current_n0;
    reg signed [15:0] current_n1;
    
    integer i;
    always @(*) begin
        current_n0 = 0;
        current_n1 = 0;
        for (i = 0; i < 8; i = i + 1) begin
            if (in_spikes[i]) begin
                current_n0 = current_n0 + w0[i];
                current_n1 = current_n1 + w1[i];
            end
        end
    end

    reg signed [15:0] current_n0_reg;
    reg signed [15:0] current_n1_reg;
    reg               valid_reg;

    always @(posedge clk) begin
        if (rst) begin
            current_n0_reg <= 0;
            current_n1_reg <= 0;
            valid_reg      <= 0;
            valid_out      <= 0;
        end else begin
            valid_reg <= valid_in;
            valid_out <= valid_reg; 
            if (valid_in) begin
                current_n0_reg <= current_n0;
                current_n1_reg <= current_n1;
            end else begin
                current_n0_reg <= 0;
                current_n1_reg <= 0;
            end
        end
    end

    // Use THRESHOLD = 1000 so that it takes multiple cycles to fire.
    snn_tff_neuron_v003 #(
        .DATA_WIDTH(16),
        .LEAK_SHIFT(3),      
        .THRESHOLD(16'sd1000)  
    ) neuron_safe (
        .clk(clk),
        .rst(rst),
        .syn_current(current_n0_reg),
        .valid_in(valid_reg),
        .spike_out(out_spikes[0])
    );

    snn_tff_neuron_v003 #(
        .DATA_WIDTH(16),
        .LEAK_SHIFT(3),
        .THRESHOLD(16'sd1000)
    ) neuron_anomaly (
        .clk(clk),
        .rst(rst),
        .syn_current(current_n1_reg),
        .valid_in(valid_reg),
        .spike_out(out_spikes[1])
    );

endmodule

.history_payload/flattened/ev17/tb/tb_snn_layer_v003.v
`timescale 1ns / 1ps

module tb_snn_layer_v003;

    reg clk;
    reg rst;
    
    reg [7:0] in_spikes;
    reg       valid_in;
    
    wire [1:0] out_spikes;
    wire       valid_out;

    snn_tff_layer_v003 uut (
        .clk(clk),
        .rst(rst),
        .in_spikes(in_spikes),
        .valid_in(valid_in),
        .out_spikes(out_spikes),
        .valid_out(valid_out)
    );

    initial begin
        $dumpfile("tb_snn_layer_v003.vcd");
        $dumpvars(0, tb_snn_layer_v003);
        clk = 0;
        forever #3.2 clk = ~clk; // 156.25 MHz
    end
    
    always @(posedge clk) begin
        if (valid_out) begin
            if (out_spikes[0]) $display("[%0t] SNN FIRED: Safe Traffic Detected", $time);
            if (out_spikes[1]) $display("[%0t] SNN FIRED: Anomaly/Threat Detected (DROP)", $time);
        end
    end

    task inject_spikes(input [7:0] pattern, input integer cycles);
        integer i;
        begin
            for (i=0; i<cycles; i=i+1) begin
                @(posedge clk);
                valid_in <= 1;
                in_spikes <= pattern;
            end
            @(posedge clk);
            valid_in <= 0;
            in_spikes <= 0;
        end
    endtask

    initial begin
        rst = 1;
        valid_in = 0;
        in_spikes = 0;
        
        #100;
        rst = 0;
        #20;
        
        $display("[%0t] Experiment 1: Normal Traffic Pattern (Excites Safe Neuron)", $time);
        // Safe neuron max sum is 150. Threshold is 1000. Needs roughly 7-8 cycles of continuous input to fire.
        inject_spikes(8'b11000011, 20); 
        
        #150;
        
        $display("[%0t] Experiment 2: Anomaly Traffic Pattern (Excites Anomaly Neuron)", $time);
        // Anomaly neuron max sum is 410. Threshold is 1000. Needs roughly 3 cycles to fire.
        inject_spikes(8'b00111100, 15);
        
        #150;
        
        $display("[%0t] Experiment 3: Low-rate Anomaly (Should leak and not fire, testing BUG-004 fix)", $time);
        // We inject 1 spike (sum=410), then wait 5 cycles. Leak should reduce it heavily.
        // It should never reach 1000.
        inject_spikes(8'b00111100, 1);
        #32; 
        inject_spikes(8'b00111100, 1);
        #32;
        inject_spikes(8'b00111100, 1);
        #32;
        inject_spikes(8'b00111100, 1);
        #32;
        inject_spikes(8'b00111100, 1);
        
        #200;
        $finish;
    end

endmodule

.history_payload/flattened/ev17/sim/tb_snn_layer_v003.vcd
$date
	Fri Jun 26 17:37:41 2026
$end
$version
	Icarus Verilog
$end
$timescale
	1ps
$end
$scope module tb_snn_layer_v003 $end
$var wire 1 ! valid_out $end
$var wire 2 " out_spikes [1:0] $end
$var reg 1 # clk $end
$var reg 8 $ in_spikes [7:0] $end
$var reg 1 % rst $end
$var reg 1 & valid_in $end
$scope module uut $end
$var wire 1 # clk $end
$var wire 8 ' in_spikes [7:0] $end
$var wire 1 % rst $end
$var wire 1 & valid_in $end
$var wire 2 ( out_spikes [1:0] $end
$var reg 16 ) current_n0 [15:0] $end
$var reg 16 * current_n0_reg [15:0] $end
$var reg 16 + current_n1 [15:0] $end
$var reg 16 , current_n1_reg [15:0] $end
$var reg 1 ! valid_out $end
$var reg 1 - valid_reg $end
$var integer 32 . i [31:0] $end
$scope module neuron_anomaly $end
$var wire 1 # clk $end
$var wire 1 % rst $end
$var wire 16 / syn_current [15:0] $end
$var wire 1 - valid_in $end
$var wire 16 0 u_temp [15:0] $end
$var wire 16 1 u_decayed [15:0] $end
$var wire 16 2 syn_input [15:0] $end
$var wire 16 3 leak_amount [15:0] $end
$var parameter 32 4 DATA_WIDTH $end
$var parameter 32 5 LEAK_SHIFT $end
$var parameter 16 6 THRESHOLD $end
$var reg 16 7 membrane_u [15:0] $end
$var reg 1 8 spike_out $end
$upscope $end
$scope module neuron_safe $end
$var wire 1 # clk $end
$var wire 1 % rst $end
$var wire 16 9 syn_current [15:0] $end
$var wire 1 - valid_in $end
$var wire 16 : u_temp [15:0] $end
$var wire 16 ; u_decayed [15:0] $end
$var wire 16 < syn_input [15:0] $end
$var wire 16 = leak_amount [15:0] $end
$var parameter 32 > DATA_WIDTH $end
$var parameter 32 ? LEAK_SHIFT $end
$var parameter 16 @ THRESHOLD $end
$var reg 16 A membrane_u [15:0] $end
$var reg 1 B spike_out $end
$upscope $end
$upscope $end
$scope task inject_spikes $end
$var reg 8 C pattern [7:0] $end
$var integer 32 D cycles [31:0] $end
$var integer 32 E i [31:0] $end
$upscope $end
$upscope $end
$enddefinitions $end
$comment Show the parameter values. $end
$dumpall
b1111101000 @
b11 ?
b10000 >
b1111101000 6
b11 5
b10000 4
$end
#0
$dumpvars
bx E
bx D
bx C
xB
bx A
bx =
bx <
bx ;
bx :
bx 9
x8
bx 7
bx 3
bx 2
bx 1
bx 0
bx /
b1000 .
x-
bx ,
b0 +
bx *
b0 )
bx (
b0 '
0&
1%
b0 $
0#
bx "
x!
$end
#3200
b0 :
b0 ;
b0 =
b0 0
b0 1
b0 3
b0 2
b0 <
0B
b0 A
b0 "
b0 (
08
b0 7
0!
0-
b0 ,
b0 /
b0 *
b0 9
1#
#6400
0#
#9600
1#
#12800
0#
#16000
1#
#19200
0#
#22400
1#
#25600
0#
#28800
1#
#32000
0#
#35200
1#
#38400
0#
#41600
1#
#44800
0#
#48000
1#
#51200
0#
#54400
1#
#57600
0#
#60800
1#
#64000
0#
#67200
1#
#70400
0#
#73600
1#
#76800
0#
#80000
1#
#83200
0#
#86400
1#
#89600
0#
#92800
1#
#96000
0#
#99200
1#
#100000
0%
#102400
0#
#105600
1#
#108800
0#
#112000
1#
#115200
0#
#118400
1#
#120000
b0 E
b10100 D
b11000011 C
#121600
0#
#124800
b1111111111011000 +
b10001100 )
b1000 .
b11000011 $
b11000011 '
1&
b1 E
1#
#128000
0#
#131200
b1111111111011000 0
b1111111111011000 2
b10001100 :
b10001100 <
b1111111111011000 ,
b1111111111011000 /
b10001100 *
b10001100 9
1-
b10 E
1#
#134400
0#
#137600
b1111111111111011 3
b10001 =
1!
b1111111110110101 0
b1111111111011101 1
b1111111111011000 7
b100000111 :
b1111011 ;
b10001100 A
b11 E
1#
#140800
0#
#144000
b100000 =
b1111111111110110 3
b101110011 :
b11100111 ;
b100000111 A
b1111111110010111 0
b1111111110111111 1
b1111111110110101 7
b100 E
1#
#147200
0#
#150400
b1111111111110010 3
b101110 =
b1111111101111101 0
b1111111110100101 1
b1111111110010111 7
b111010001 :
b101000101 ;
b101110011 A
b101 E
1#
#153600
0#
#156800
b111010 =
b1111111111101111 3
b1000100011 :
b110010111 ;
b111010001 A
b1111111101100110 0
b1111111110001110 1
b1111111101111101 7
b110 E
1#
#160000
0#
#163200
b1111111111101100 3
b1000100 =
b1111111101010010 0
b1111111101111010 1
b1111111101100110 7
b1001101011 :
b111011111 ;
b1000100011 A
b111 E
1#
#166400
0#
#169600
b1001101 =
b1111111111101010 3
b1010101010 :
b1000011110 ;
b1001101011 A
b1111111101000000 0
b1111111101101000 1
b1111111101010010 7
b1000 E
1#
#172800
0#
#176000
b1111111111101000 3
b1010101 =
b1111111100110000 0
b1111111101011000 1
b1111111101000000 7
b1011100001 :
b1001010101 ;
b1010101010 A
b1001 E
1#
#179200
0#
#182400
b1011100 =
b1111111111100110 3
b1100010001 :
b1010000101 ;
b1011100001 A
b1111111100100010 0
b1111111101001010 1
b1111111100110000 7
b1010 E
1#
#185600
0#
#188800
b1111111111100100 3
b1100010 =
b1111111100010110 0
b1111111100111110 1
b1111111100100010 7
b1100111011 :
b1010101111 ;
b1100010001 A
b1011 E
1#
#192000
0#
#195200
b1100111 =
b1111111111100010 3
b1101100000 :
b1011010100 ;
b1100111011 A
b1111111100001100 0
b1111111100110100 1
b1111111100010110 7
b1100 E
1#
#198400
0#
#201600
b1111111111100001 3
b1101100 =
b1111111100000011 0
b1111111100101011 1
b1111111100001100 7
b1110000000 :
b1011110100 ;
b1101100000 A
b1101 E
1#
#204800
0#
#208000
b1110000 =
b1111111111100000 3
b1110011100 :
b1100010000 ;
b1110000000 A
b1111111011111011 0
b1111111100100011 1
b1111111100000011 7
b1110 E
1#
#211200
0#
#214400
b1111111111011111 3
b1110011 =
b1111111011110100 0
b1111111100011100 1
b1111111011111011 7
b1110110101 :
b1100101001 ;
b1110011100 A
b1111 E
1#
#217600
0#
#220800
b1110110 =
b1111111111011110 3
b1111001011 :
b1100111111 ;
b1110110101 A
b1111111011101110 0
b1111111100010110 1
b1111111011110100 7
b10000 E
1#
#224000
0#
#227200
b1111111111011101 3
b1111001 =
b1111111011101001 0
b1111111100010001 1
b1111111011101110 7
b1111011110 :
b1101010010 ;
b1111001011 A
b10001 E
1#
#230400
0#
#233600
b1111011 =
b1111101111 :
b1101100011 ;
b1111011110 A
b1111111011100100 0
b1111111100001100 1
b1111111011101001 7
b10010 E
1#
#236800
0#
#240000
b1111111111011100 3
b0 =
b1111111011100000 0
b1111111100001000 1
b1111111011100100 7
b10001100 :
b0 ;
b0 A
b1 "
b1 (
1B
b10011 E
1#
#243200
0#
#246400
b10001 =
b100000111 :
b1111011 ;
b10001100 A
b0 "
b0 (
0B
b1111111011011100 0
b1111111100000100 1
b1111111011100000 7
b10100 E
1#
#249600
0#
#252800
b1111111111011011 3
b100000 =
b1000 .
b0 +
b0 )
b1111111011011001 0
b1111111100000001 1
b1111111011011100 7
b101110011 :
b11100111 ;
b100000111 A
b0 $
b0 '
0&
1#
#256000
0#
#259200
b101110 =
b0 2
b0 <
b101000101 :
b101000101 ;
b101110011 A
b1111111011111110 0
b1111111011111110 1
b1111111011011001 7
b0 ,
b0 /
b0 *
b0 9
0-
1#
#262400
0#
#265600
b1111111111011111 3
b101000 =
0!
b1111111100011111 0
b1111111100011111 1
b1111111011111110 7
b100011101 :
b100011101 ;
b101000101 A
1#
#268800
0#
#272000
b100011 =
b1111111111100011 3
b11111010 :
b11111010 ;
b100011101 A
b1111111100111100 0
b1111111100111100 1
b1111111100011111 7
1#
#275200
0#
#278400
b1111111111100111 3
b11111 =
b1111111101010101 0
b1111111101010101 1
b1111111100111100 7
b11011011 :
b11011011 ;
b11111010 A
1#
#281600
0#
#284800
b11011 =
b1111111111101010 3
b11000000 :
b11000000 ;
b11011011 A
b1111111101101011 0
b1111111101101011 1
b1111111101010101 7
1#
#288000
0#
#291200
b1111111111101101 3
b11000 =
b1111111101111110 0
b1111111101111110 1
b1111111101101011 7
b10101000 :
b10101000 ;
b11000000 A
1#
#294400
0#
#297600
b10101 =
b1111111111101111 3
b10010011 :
b10010011 ;
b10101000 A
b1111111110001111 0
b1111111110001111 1
b1111111101111110 7
1#
#300800
0#
#304000
b1111111111110001 3
b10010 =
b1111111110011110 0
b1111111110011110 1
b1111111110001111 7
b10000001 :
b10000001 ;
b10010011 A
1#
#307200
0#
#310400
b10000 =
b1111111111110011 3
b1110001 :
b1110001 ;
b10000001 A
b1111111110101011 0
b1111111110101011 1
b1111111110011110 7
1#
#313600
0#
#316800
b1111111111110101 3
b1110 =
b1111111110110110 0
b1111111110110110 1
b1111111110101011 7
b1100011 :
b1100011 ;
b1110001 A
1#
#320000
0#
#323200
b1100 =
b1111111111110110 3
b1010111 :
b1010111 ;
b1100011 A
b1111111111000000 0
b1111111111000000 1
b1111111110110110 7
1#
#326400
0#
#329600
b1111111111111000 3
b1010 =
b1111111111001000 0
b1111111111001000 1
b1111111111000000 7
b1001101 :
b1001101 ;
b1010111 A
1#
#332800
0#
#336000
b1001 =
b1111111111111001 3
b1000100 :
b1000100 ;
b1001101 A
b1111111111001111 0
b1111111111001111 1
b1111111111001000 7
1#
#339200
0#
#342400
b1000 =
b1111111111010110 0
b1111111111010110 1
b1111111111001111 7
b111100 :
b111100 ;
b1000100 A
1#
#345600
0#
#348800
b111 =
b1111111111111010 3
b110101 :
b110101 ;
b111100 A
b1111111111011100 0
b1111111111011100 1
b1111111111010110 7
1#
#352000
0#
#355200
b1111111111111011 3
b110 =
b1111111111100001 0
b1111111111100001 1
b1111111111011100 7
b101111 :
b101111 ;
b110101 A
1#
#358400
0#
#361600
b101 =
b1111111111111100 3
b101010 :
b101010 ;
b101111 A
b1111111111100101 0
b1111111111100101 1
b1111111111100001 7
1#
#364800
0#
#368000
b1111111111101001 0
b1111111111101001 1
b1111111111100101 7
b100101 :
b100101 ;
b101010 A
1#
#371200
0#
#374400
b100 =
b1111111111111101 3
b100001 :
b100001 ;
b100101 A
b1111111111101100 0
b1111111111101100 1
b1111111111101001 7
1#
#377600
0#
#380800
b1111111111101111 0
b1111111111101111 1
b1111111111101100 7
b11101 :
b11101 ;
b100001 A
1#
#384000
0#
#387200
b11 =
b11010 :
b11010 ;
b11101 A
b1111111111110010 0
b1111111111110010 1
b1111111111101111 7
1#
#390400
0#
#393600
b1111111111111110 3
b1111111111110100 0
b1111111111110100 1
b1111111111110010 7
b10111 :
b10111 ;
b11010 A
1#
#396800
0#
#400000
b10 =
b10101 :
b10101 ;
b10111 A
b1111111111110110 0
b1111111111110110 1
b1111111111110100 7
1#
#402800
b0 E
b1111 D
b111100 C
#403200
0#
#406400
b1111111101110100 )
b110011010 +
b1000 .
b1111111111111000 0
b1111111111111000 1
b1111111111110110 7
b10011 :
b10011 ;
b10101 A
b111100 $
b111100 '
1&
b1 E
1#
#409600
0#
#412800
b1111111111111111 3
b110011010 2
b1111111101110100 <
b1111111110000101 :
b10001 ;
b10011 A
b110010011 0
b1111111111111001 1
b1111111111111000 7
b110011010 ,
b110011010 /
b1111111101110100 *
b1111111101110100 9
1-
b10 E
1#
#416000
0#
#419200
b110010 3
b1111111111110000 =
1!
b1011111011 0
b101100001 1
b110010011 7
b1111111100001001 :
b1111111110010101 ;
b1111111110000101 A
b11 E
1#
#422400
0#
#425600
b1111111111100001 =
b1011111 3
b1111111010011100 :
b1111111100101000 ;
b1111111100001001 A
b10000110110 0
b1010011100 1
b1011111011 7
b100 E
1#
#428800
0#
#432000
b0 3
b1111111111010011 =
b110011010 0
b0 1
b0 7
b10 "
b10 (
18
b1111111000111101 :
b1111111011001001 ;
b1111111010011100 A
b101 E
1#
#435200
0#
#438400
b1111111111000111 =
b110011 3
b1111110111101010 :
b1111111001110110 ;
b1111111000111101 A
b1100000001 0
b101100111 1
b110011010 7
b0 "
b0 (
08
b110 E
1#
#441600
0#
#444800
b1100000 3
b1111111110111101 =
b10000111011 0
b1010100001 1
b1100000001 7
b1111110110100001 :
b1111111000101101 ;
b1111110111101010 A
b111 E
1#
#448000
0#
#451200
b1111111110110100 =
b0 3
b1111110101100001 :
b1111110111101101 ;
b1111110110100001 A
b110011010 0
b0 1
b0 7
b10 "
b10 (
18
b1000 E
1#
#454400
0#
#457600
b110011 3
b1111111110101100 =
b1100000001 0
b101100111 1
b110011010 7
b0 "
b0 (
08
b1111110100101001 :
b1111110110110101 ;
b1111110101100001 A
b1001 E
1#
#460800
0#
#464000
b1111111110100101 =
b1100000 3
b1111110011111000 :
b1111110110000100 ;
b1111110100101001 A
b10000111011 0
b1010100001 1
b1100000001 7
b1010 E
1#
#467200
0#
#470400
b0 3
b1111111110011111 =
b110011010 0
b0 1
b0 7
b10 "
b10 (
18
b1111110011001101 :
b1111110101011001 ;
b1111110011111000 A
b1011 E
1#
#473600
0#
#476800
b1111111110011001 =
b110011 3
b1111110010101000 :
b1111110100110100 ;
b1111110011001101 A
b1100000001 0
b101100111 1
b110011010 7
b0 "
b0 (
08
b1100 E
1#
#480000
0#
#483200
b1100000 3
b1111111110010101 =
b10000111011 0
b1010100001 1
b1100000001 7
b1111110010000111 :
b1111110100010011 ;
b1111110010101000 A
b1101 E
1#
#486400
0#
#489600
b1111111110010000 =
b0 3
b1111110001101011 :
b1111110011110111 ;
b1111110010000111 A
b110011010 0
b0 1
b0 7
b10 "
b10 (
18
b1110 E
1#
#492800
0#
#496000
b110011 3
b1111111110001101 =
b1100000001 0
b101100111 1
b110011010 7
b0 "
b0 (
08
b1111110001010010 :
b1111110011011110 ;
b1111110001101011 A
b1111 E
1#
#499200
0#
#502400
b1000 .
b0 +
b0 )
b1111111110001010 =
b1100000 3
b0 $
b0 '
0&
b1111110000111100 :
b1111110011001000 ;
b1111110001010010 A
b10000111011 0
b1010100001 1
b1100000001 7
1#
#505600
0#
#508800
b0 2
b0 <
b0 3
b1111111110000111 =
b0 ,
b0 /
b0 *
b0 9
0-
b0 0
b0 1
b0 7
b10 "
b10 (
18
b1111110010110101 :
b1111110010110101 ;
b1111110000111100 A
1#
#512000
0#
#515200
b1111111110010110 =
b1111110100011111 :
b1111110100011111 ;
b1111110010110101 A
b0 "
b0 (
08
0!
1#
#518400
0#
#521600
b1111111110100011 =
b1111110101111100 :
b1111110101111100 ;
b1111110100011111 A
1#
#524800
0#
#528000
b1111111110101111 =
b1111110111001101 :
b1111110111001101 ;
b1111110101111100 A
1#
#531200
0#
#534400
b1111111110111001 =
b1111111000010100 :
b1111111000010100 ;
b1111110111001101 A
1#
#537600
0#
#540800
b1111111111000010 =
b1111111001010010 :
b1111111001010010 ;
b1111111000010100 A
1#
#544000
0#
#547200
b1111111111001010 =
b1111111010001000 :
b1111111010001000 ;
b1111111001010010 A
1#
#550400
0#
#553600
b1111111111010001 =
b1111111010110111 :
b1111111010110111 ;
b1111111010001000 A
1#
#556800
0#
#560000
b1111111111010110 =
b1111111011100001 :
b1111111011100001 ;
b1111111010110111 A
1#
#563200
0#
#566400
b1111111111011100 =
b1111111100000101 :
b1111111100000101 ;
b1111111011100001 A
1#
#569600
0#
#572800
b1111111111100000 =
b1111111100100101 :
b1111111100100101 ;
b1111111100000101 A
1#
#576000
0#
#579200
b1111111111100100 =
b1111111101000001 :
b1111111101000001 ;
b1111111100100101 A
1#
#582400
0#
#585600
b1111111111101000 =
b1111111101011001 :
b1111111101011001 ;
b1111111101000001 A
1#
#588800
0#
#592000
b1111111111101011 =
b1111111101101110 :
b1111111101101110 ;
b1111111101011001 A
1#
#595200
0#
#598400
b1111111111101101 =
b1111111110000001 :
b1111111110000001 ;
b1111111101101110 A
1#
#601600
0#
#604800
b1111111111110000 =
b1111111110010001 :
b1111111110010001 ;
b1111111110000001 A
1#
#608000
0#
#611200
b1111111111110010 =
b1111111110011111 :
b1111111110011111 ;
b1111111110010001 A
1#
#614400
0#
#617600
b1111111111110011 =
b1111111110101100 :
b1111111110101100 ;
b1111111110011111 A
1#
#620800
0#
#624000
b1111111111110101 =
b1111111110110111 :
b1111111110110111 ;
b1111111110101100 A
1#
#627200
0#
#630400
b1111111111110110 =
b1111111111000001 :
b1111111111000001 ;
b1111111110110111 A
1#
#633600
0#
#636800
b1111111111111000 =
b1111111111001001 :
b1111111111001001 ;
b1111111111000001 A
1#
#640000
0#
#643200
b1111111111111001 =
b1111111111010000 :
b1111111111010000 ;
b1111111111001001 A
1#
#646400
0#
#649600
b1111111111111010 =
b1111111111010110 :
b1111111111010110 ;
b1111111111010000 A
1#
#652400
b0 E
b1 D
#652800
0#
#656000
b1111111101110100 )
b110011010 +
b1000 .
b1111111111011100 :
b1111111111011100 ;
b1111111111010110 A
b111100 $
b111100 '
1&
b1 E
1#
#659200
0#
#662400
b1000 .
b0 +
b0 )
b110011010 0
b110011010 2
b1111111101110100 <
b1111111111111011 =
b0 $
b0 '
0&
b110011010 ,
b110011010 /
b1111111101110100 *
b1111111101110100 9
1-
b1111111101010101 :
b1111111111100001 ;
b1111111111011100 A
1#
#665600
0#
#668800
b1111111111101010 =
b110011 3
b0 2
b0 <
b1111111101101011 :
b1111111101101011 ;
b1111111101010101 A
b101100111 0
b101100111 1
b110011010 7
b0 ,
b0 /
b0 *
b0 9
1!
0-
1#
#672000
0#
#675200
b101100 3
b1111111111101101 =
0!
b100111011 0
b100111011 1
b101100111 7
b1111111101111110 :
b1111111101111110 ;
b1111111101101011 A
1#
#678400
0#
#681600
b1111111111101111 =
b100111 3
b1111111110001111 :
b1111111110001111 ;
b1111111101111110 A
b100010100 0
b100010100 1
b100111011 7
1#
#684800
0#
#688000
b100010 3
b1111111111110001 =
b11110010 0
b11110010 1
b100010100 7
b1111111110011110 :
b1111111110011110 ;
b1111111110001111 A
1#
#691200
0#
#694400
b1111111111110011 =
b11110 3
b1111111101110100 )
b110011010 +
b1000 .
b1111111110101011 :
b1111111110101011 ;
b1111111110011110 A
b11010100 0
b11010100 1
b11110010 7
b111100 $
b111100 '
1&
1#
b1 E
#697600
0#
#700800
b1000 .
b0 +
b0 )
b110011010 2
b1111111101110100 <
b11010 3
b1111111111110101 =
b0 $
b0 '
0&
b110011010 ,
b110011010 /
b1111111101110100 *
b1111111101110100 9
1-
b1001010100 0
b10111010 1
b11010100 7
b1111111100101010 :
b1111111110110110 ;
b1111111110101011 A
1#
#704000
0#
#707200
b1111111111100101 =
b1001010 3
b0 2
b0 <
b1111111101000101 :
b1111111101000101 ;
b1111111100101010 A
b1000001010 0
b1000001010 1
b1001010100 7
b0 ,
b0 /
b0 *
b0 9
1!
0-
1#
#710400
0#
#713600
b1000001 3
b1111111111101000 =
0!
b111001001 0
b111001001 1
b1000001010 7
b1111111101011101 :
b1111111101011101 ;
b1111111101000101 A
1#
#716800
0#
#720000
b1111111111101011 =
b111001 3
b1111111101110010 :
b1111111101110010 ;
b1111111101011101 A
b110010000 0
b110010000 1
b111001001 7
1#
#723200
0#
#726400
b110010 3
b1111111111101110 =
b101011110 0
b101011110 1
b110010000 7
b1111111110000100 :
b1111111110000100 ;
b1111111101110010 A
1#
#729600
0#
#732800
b1111111111110000 =
b101011 3
b1111111101110100 )
b110011010 +
b1000 .
b1111111110010100 :
b1111111110010100 ;
b1111111110000100 A
b100110011 0
b100110011 1
b101011110 7
b111100 $
b111100 '
1&
1#
b1 E
#736000
0#
#739200
b1000 .
b0 +
b0 )
b110011010 2
b1111111101110100 <
b100110 3
b1111111111110010 =
b0 $
b0 '
0&
b110011010 ,
b110011010 /
b1111111101110100 *
b1111111101110100 9
1-
b1010100111 0
b100001101 1
b100110011 7
b1111111100010110 :
b1111111110100010 ;
b1111111110010100 A
1#
#742400
0#
#745600
b1111111111100010 =
b1010100 3
b0 2
b0 <
b1111111100110100 :
b1111111100110100 ;
b1111111100010110 A
b1001010011 0
b1001010011 1
b1010100111 7
b0 ,
b0 /
b0 *
b0 9
1!
0-
1#
#748800
0#
#752000
b1001010 3
b1111111111100110 =
0!
b1000001001 0
b1000001001 1
b1001010011 7
b1111111101001110 :
b1111111101001110 ;
b1111111100110100 A
1#
#755200
0#
#758400
b1111111111101001 =
b1000001 3
b1111111101100101 :
b1111111101100101 ;
b1111111101001110 A
b111001000 0
b111001000 1
b1000001001 7
1#
#761600
0#
#764800
b111001 3
b1111111111101100 =
b110001111 0
b110001111 1
b111001000 7
b1111111101111001 :
b1111111101111001 ;
b1111111101100101 A
1#
#768000
0#
#771200
b1111111111101111 =
b110001 3
b1111111101110100 )
b110011010 +
b1000 .
b1111111110001010 :
b1111111110001010 ;
b1111111101111001 A
b101011110 0
b101011110 1
b110001111 7
b111100 $
b111100 '
1&
1#
b1 E
#774400
0#
#777600
b1000 .
b0 +
b0 )
b110011010 2
b1111111101110100 <
b101011 3
b1111111111110001 =
b0 $
b0 '
0&
b110011010 ,
b110011010 /
b1111111101110100 *
b1111111101110100 9
1-
b1011001101 0
b100110011 1
b101011110 7
b1111111100001101 :
b1111111110011001 ;
b1111111110001010 A
1#
#780800
0#
#784000
b1111111111100001 =
b1011001 3
b0 2
b0 <
b1111111100101100 :
b1111111100101100 ;
b1111111100001101 A
b1001110100 0
b1001110100 1
b1011001101 7
b0 ,
b0 /
b0 *
b0 9
1!
0-
1#
#787200
0#
#790400
b1001110 3
b1111111111100101 =
0!
b1000100110 0
b1000100110 1
b1001110100 7
b1111111101000111 :
b1111111101000111 ;
b1111111100101100 A
1#
#793600
0#
#796800
b1111111111101000 =
b1000100 3
b1111111101011111 :
b1111111101011111 ;
b1111111101000111 A
b111100010 0
b111100010 1
b1000100110 7
1#
#800000
0#
#803200
b111100 3
b1111111111101011 =
b110100110 0
b110100110 1
b111100010 7
b1111111101110100 :
b1111111101110100 ;
b1111111101011111 A
1#
#806400
0#
#809600
b1111111111101110 =
b110100 3
b1111111101110100 )
b110011010 +
b1000 .
b1111111110000110 :
b1111111110000110 ;
b1111111101110100 A
b101110010 0
b101110010 1
b110100110 7
b111100 $
b111100 '
1&
1#
b1 E
#812800
0#
#816000
b1000 .
b0 +
b0 )
b110011010 2
b1111111101110100 <
b101110 3
b1111111111110000 =
b0 $
b0 '
0&
b110011010 ,
b110011010 /
b1111111101110100 *
b1111111101110100 9
1-
b1011011110 0
b101000100 1
b101110010 7
b1111111100001010 :
b1111111110010110 ;
b1111111110000110 A
1#
#819200
0#
#822400
b1111111111100001 =
b1011011 3
b0 2
b0 <
b1111111100101001 :
b1111111100101001 ;
b1111111100001010 A
b1010000011 0
b1010000011 1
b1011011110 7
b0 ,
b0 /
b0 *
b0 9
1!
0-
1#
#825600
0#
#828800
b1010000 3
b1111111111100101 =
0!
b1000110011 0
b1000110011 1
b1010000011 7
b1111111101000100 :
b1111111101000100 ;
b1111111100101001 A
1#
#832000
0#
#835200
b1111111111101000 =
b1000110 3
b1111111101011100 :
b1111111101011100 ;
b1111111101000100 A
b111101101 0
b111101101 1
b1000110011 7
1#
#838400
0#
#841600
b111101 3
b1111111111101011 =
b110110000 0
b110110000 1
b111101101 7
b1111111101110001 :
b1111111101110001 ;
b1111111101011100 A
1#
#844800
0#
#848000
b1111111111101110 =
b110110 3
b1111111110000011 :
b1111111110000011 ;
b1111111101110001 A
b101111010 0
b101111010 1
b110110000 7
1#
#851200
0#
#854400
b101111 3
b1111111111110000 =
b101001011 0
b101001011 1
b101111010 7
b1111111110010011 :
b1111111110010011 ;
b1111111110000011 A
1#
#857600
0#
#860800
b1111111111110010 =
b101001 3
b1111111110100001 :
b1111111110100001 ;
b1111111110010011 A
b100100010 0
b100100010 1
b101001011 7
1#
