.history_payload/blob_store/2ae9cdef1ff0d5a3666a87f0dbf1df83_ha_tff_hash_v001.v
`timescale 1ns / 1ps

module ha_tff_hash_v001 (
    input  wire         clk,
    input  wire         rst,
    
    input  wire [103:0] tuple_in,
    input  wire         valid_in,
    
    output reg  [11:0]  hash_0,
    output reg  [11:0]  hash_1,
    output reg  [11:0]  hash_2,
    output reg  [11:0]  hash_3,
    output reg          valid_out
);

    // Combinatorial XOR arrays for 4 independent hashes
    // In a real synthesis environment, these would be generated by a Python script 
    // to guarantee avalanching and independence. For v001, we use static XOR folding.
    
    wire [11:0] h0_comb;
    wire [11:0] h1_comb;
    wire [11:0] h2_comb;
    wire [11:0] h3_comb;
    
    // Seed 0: Linear folding
    assign h0_comb = tuple_in[11:0] ^ tuple_in[23:12] ^ tuple_in[35:24] ^ 
                     tuple_in[47:36] ^ tuple_in[59:48] ^ tuple_in[71:60] ^ 
                     tuple_in[83:72] ^ tuple_in[95:84] ^ {4'hA, tuple_in[103:96]};

    // Seed 1: Bit-reversed folding
    wire [103:0] rev_tuple;
    genvar i;
    generate
        for (i=0; i<104; i=i+1) begin : rev
            assign rev_tuple[i] = tuple_in[103-i];
        end
    endgenerate
    
    assign h1_comb = rev_tuple[11:0] ^ rev_tuple[23:12] ^ rev_tuple[35:24] ^ 
                     rev_tuple[47:36] ^ rev_tuple[59:48] ^ rev_tuple[71:60] ^ 
                     rev_tuple[83:72] ^ rev_tuple[95:84] ^ {4'h5, rev_tuple[103:96]};

    // Seed 2: Shifted by 3
    assign h2_comb = h0_comb ^ (h0_comb << 3) ^ (h0_comb >> 5) ^ 12'h3A7;
    
    // Seed 3: Shifted and mixed with h1
    assign h3_comb = h1_comb ^ (h0_comb << 7) ^ (h1_comb >> 2) ^ 12'hC2F;

    always @(posedge clk) begin
        if (rst) begin
            hash_0    <= 0;
            hash_1    <= 0;
            hash_2    <= 0;
            hash_3    <= 0;
            valid_out <= 0;
        end else begin
            valid_out <= valid_in;
            if (valid_in) begin
                hash_0 <= h0_comb;
                hash_1 <= h1_comb;
                hash_2 <= h2_comb;
                hash_3 <= h3_comb;
            end
        end
    end

endmodule

.history_payload/Master_Archive/Engineering_History/06_Testbenches/tb_v003/tb_ha_tff_hash_v001.v
`timescale 1ns / 1ps

module tb_ha_tff_hash_v001;

    reg clk;
    reg rst;
    
    reg [103:0] tuple_in;
    reg         valid_in;
    
    wire [11:0] hash_0;
    wire [11:0] hash_1;
    wire [11:0] hash_2;
    wire [11:0] hash_3;
    wire        valid_out;

    ha_tff_hash_v001 uut (
        .clk(clk),
        .rst(rst),
        .tuple_in(tuple_in),
        .valid_in(valid_in),
        .hash_0(hash_0),
        .hash_1(hash_1),
        .hash_2(hash_2),
        .hash_3(hash_3),
        .valid_out(valid_out)
    );

    initial begin
        $dumpfile("tb_ha_tff_hash_v001.vcd");
        $dumpvars(0, tb_ha_tff_hash_v001);
        clk = 0;
        forever #3.2 clk = ~clk; // 156.25 MHz
    end

    always @(posedge clk) begin
        if (valid_out) begin
            $display("[%0t] Hash Computed! Tuple: %x", $time, tuple_in);
            $display("  H0: %x, H1: %x, H2: %x, H3: %x", hash_0, hash_1, hash_2, hash_3);
        end
    end

    task test_tuple(input [103:0] din);
        begin
            @(posedge clk);
            valid_in <= 1;
            tuple_in <= din;
            @(posedge clk);
            valid_in <= 0;
            // Wait for pipeline
            @(posedge clk);
            @(posedge clk);
        end
    endtask

    initial begin
        rst = 1;
        valid_in = 0;
        tuple_in = 0;
        
        #100;
        rst = 0;
        #20;
        
        // Test 1: All zeros
        test_tuple(104'h0);
        
        // Test 2: Sequential
        test_tuple(104'h0102030405060708090A0B0C0D);
        
        // Test 3: Random IP/Port combo
        // Src IP: 192.168.1.1 (C0A80101), Dst: 10.0.0.1 (0A000001)
        // Src Port: 1234 (04D2), Dst Port: 80 (0050), Proto: UDP (11)
        test_tuple({32'hC0A80101, 32'h0A000001, 16'h04D2, 16'h0050, 8'h11});
        
        // Test 4: Slight variation (Port 81)
        test_tuple({32'hC0A80101, 32'h0A000001, 16'h04D2, 16'h0051, 8'h11});
        
        #100;
        $finish;
    end

endmodule

.history_payload/flattened/ev04/sim/tb_ha_tff_hash_v001.vcd
$date
	Fri Jun 26 17:03:37 2026
$end
$version
	Icarus Verilog
$end
$timescale
	1ps
$end
$scope module tb_ha_tff_hash_v001 $end
$var wire 1 ! valid_out $end
$var wire 12 " hash_3 [11:0] $end
$var wire 12 # hash_2 [11:0] $end
$var wire 12 $ hash_1 [11:0] $end
$var wire 12 % hash_0 [11:0] $end
$var reg 1 & clk $end
$var reg 1 ' rst $end
$var reg 104 ( tuple_in [103:0] $end
$var reg 1 ) valid_in $end
$scope module uut $end
$var wire 1 & clk $end
$var wire 12 * h0_comb [11:0] $end
$var wire 12 + h1_comb [11:0] $end
$var wire 12 , h2_comb [11:0] $end
$var wire 12 - h3_comb [11:0] $end
$var wire 1 ' rst $end
$var wire 104 . tuple_in [103:0] $end
$var wire 1 ) valid_in $end
$var wire 104 / rev_tuple [103:0] $end
$var reg 12 0 hash_0 [11:0] $end
$var reg 12 1 hash_1 [11:0] $end
$var reg 12 2 hash_2 [11:0] $end
$var reg 12 3 hash_3 [11:0] $end
$var reg 1 ! valid_out $end
$scope begin rev[0] $end
$var parameter 2 4 i $end
$upscope $end
$scope begin rev[1] $end
$var parameter 2 5 i $end
$upscope $end
$scope begin rev[2] $end
$var parameter 3 6 i $end
$upscope $end
$scope begin rev[3] $end
$var parameter 3 7 i $end
$upscope $end
$scope begin rev[4] $end
$var parameter 4 8 i $end
$upscope $end
$scope begin rev[5] $end
$var parameter 4 9 i $end
$upscope $end
$scope begin rev[6] $end
$var parameter 4 : i $end
$upscope $end
$scope begin rev[7] $end
$var parameter 4 ; i $end
$upscope $end
$scope begin rev[8] $end
$var parameter 5 < i $end
$upscope $end
$scope begin rev[9] $end
$var parameter 5 = i $end
$upscope $end
$scope begin rev[10] $end
$var parameter 5 > i $end
$upscope $end
$scope begin rev[11] $end
$var parameter 5 ? i $end
$upscope $end
$scope begin rev[12] $end
$var parameter 5 @ i $end
$upscope $end
$scope begin rev[13] $end
$var parameter 5 A i $end
$upscope $end
$scope begin rev[14] $end
$var parameter 5 B i $end
$upscope $end
$scope begin rev[15] $end
$var parameter 5 C i $end
$upscope $end
$scope begin rev[16] $end
$var parameter 6 D i $end
$upscope $end
$scope begin rev[17] $end
$var parameter 6 E i $end
$upscope $end
$scope begin rev[18] $end
$var parameter 6 F i $end
$upscope $end
$scope begin rev[19] $end
$var parameter 6 G i $end
$upscope $end
$scope begin rev[20] $end
$var parameter 6 H i $end
$upscope $end
$scope begin rev[21] $end
$var parameter 6 I i $end
$upscope $end
$scope begin rev[22] $end
$var parameter 6 J i $end
$upscope $end
$scope begin rev[23] $end
$var parameter 6 K i $end
$upscope $end
$scope begin rev[24] $end
$var parameter 6 L i $end
$upscope $end
$scope begin rev[25] $end
$var parameter 6 M i $end
$upscope $end
$scope begin rev[26] $end
$var parameter 6 N i $end
$upscope $end
$scope begin rev[27] $end
$var parameter 6 O i $end
$upscope $end
$scope begin rev[28] $end
$var parameter 6 P i $end
$upscope $end
$scope begin rev[29] $end
$var parameter 6 Q i $end
$upscope $end
$scope begin rev[30] $end
$var parameter 6 R i $end
$upscope $end
$scope begin rev[31] $end
$var parameter 6 S i $end
$upscope $end
$scope begin rev[32] $end
$var parameter 7 T i $end
$upscope $end
$scope begin rev[33] $end
$var parameter 7 U i $end
$upscope $end
$scope begin rev[34] $end
$var parameter 7 V i $end
$upscope $end
$scope begin rev[35] $end
$var parameter 7 W i $end
$upscope $end
$scope begin rev[36] $end
$var parameter 7 X i $end
$upscope $end
$scope begin rev[37] $end
$var parameter 7 Y i $end
$upscope $end
$scope begin rev[38] $end
$var parameter 7 Z i $end
$upscope $end
$scope begin rev[39] $end
$var parameter 7 [ i $end
$upscope $end
$scope begin rev[40] $end
$var parameter 7 \ i $end
$upscope $end
$scope begin rev[41] $end
$var parameter 7 ] i $end
$upscope $end
$scope begin rev[42] $end
$var parameter 7 ^ i $end
$upscope $end
$scope begin rev[43] $end
$var parameter 7 _ i $end
$upscope $end
$scope begin rev[44] $end
$var parameter 7 ` i $end
$upscope $end
$scope begin rev[45] $end
$var parameter 7 a i $end
$upscope $end
$scope begin rev[46] $end
$var parameter 7 b i $end
$upscope $end
$scope begin rev[47] $end
$var parameter 7 c i $end
$upscope $end
$scope begin rev[48] $end
$var parameter 7 d i $end
$upscope $end
$scope begin rev[49] $end
$var parameter 7 e i $end
$upscope $end
$scope begin rev[50] $end
$var parameter 7 f i $end
$upscope $end
$scope begin rev[51] $end
$var parameter 7 g i $end
$upscope $end
$scope begin rev[52] $end
$var parameter 7 h i $end
$upscope $end
$scope begin rev[53] $end
$var parameter 7 i i $end
$upscope $end
$scope begin rev[54] $end
$var parameter 7 j i $end
$upscope $end
$scope begin rev[55] $end
$var parameter 7 k i $end
$upscope $end
$scope begin rev[56] $end
$var parameter 7 l i $end
$upscope $end
$scope begin rev[57] $end
$var parameter 7 m i $end
$upscope $end
$scope begin rev[58] $end
$var parameter 7 n i $end
$upscope $end
$scope begin rev[59] $end
$var parameter 7 o i $end
$upscope $end
$scope begin rev[60] $end
$var parameter 7 p i $end
$upscope $end
$scope begin rev[61] $end
$var parameter 7 q i $end
$upscope $end
$scope begin rev[62] $end
$var parameter 7 r i $end
$upscope $end
$scope begin rev[63] $end
$var parameter 7 s i $end
$upscope $end
$scope begin rev[64] $end
$var parameter 8 t i $end
$upscope $end
$scope begin rev[65] $end
$var parameter 8 u i $end
$upscope $end
$scope begin rev[66] $end
$var parameter 8 v i $end
$upscope $end
$scope begin rev[67] $end
$var parameter 8 w i $end
$upscope $end
$scope begin rev[68] $end
$var parameter 8 x i $end
$upscope $end
$scope begin rev[69] $end
$var parameter 8 y i $end
$upscope $end
$scope begin rev[70] $end
$var parameter 8 z i $end
$upscope $end
$scope begin rev[71] $end
$var parameter 8 { i $end
$upscope $end
$scope begin rev[72] $end
$var parameter 8 | i $end
$upscope $end
$scope begin rev[73] $end
$var parameter 8 } i $end
$upscope $end
$scope begin rev[74] $end
$var parameter 8 ~ i $end
$upscope $end
$scope begin rev[75] $end
$var parameter 8 !" i $end
$upscope $end
$scope begin rev[76] $end
$var parameter 8 "" i $end
$upscope $end
$scope begin rev[77] $end
$var parameter 8 #" i $end
$upscope $end
$scope begin rev[78] $end
$var parameter 8 $" i $end
$upscope $end
$scope begin rev[79] $end
$var parameter 8 %" i $end
$upscope $end
$scope begin rev[80] $end
$var parameter 8 &" i $end
$upscope $end
$scope begin rev[81] $end
$var parameter 8 '" i $end
$upscope $end
$scope begin rev[82] $end
$var parameter 8 (" i $end
$upscope $end
$scope begin rev[83] $end
$var parameter 8 )" i $end
$upscope $end
$scope begin rev[84] $end
$var parameter 8 *" i $end
$upscope $end
$scope begin rev[85] $end
$var parameter 8 +" i $end
$upscope $end
$scope begin rev[86] $end
$var parameter 8 ," i $end
$upscope $end
$scope begin rev[87] $end
$var parameter 8 -" i $end
$upscope $end
$scope begin rev[88] $end
$var parameter 8 ." i $end
$upscope $end
$scope begin rev[89] $end
$var parameter 8 /" i $end
$upscope $end
$scope begin rev[90] $end
$var parameter 8 0" i $end
$upscope $end
$scope begin rev[91] $end
$var parameter 8 1" i $end
$upscope $end
$scope begin rev[92] $end
$var parameter 8 2" i $end
$upscope $end
$scope begin rev[93] $end
$var parameter 8 3" i $end
$upscope $end
$scope begin rev[94] $end
$var parameter 8 4" i $end
$upscope $end
$scope begin rev[95] $end
$var parameter 8 5" i $end
$upscope $end
$scope begin rev[96] $end
$var parameter 8 6" i $end
$upscope $end
$scope begin rev[97] $end
$var parameter 8 7" i $end
$upscope $end
$scope begin rev[98] $end
$var parameter 8 8" i $end
$upscope $end
$scope begin rev[99] $end
$var parameter 8 9" i $end
$upscope $end
$scope begin rev[100] $end
$var parameter 8 :" i $end
$upscope $end
$scope begin rev[101] $end
$var parameter 8 ;" i $end
$upscope $end
$scope begin rev[102] $end
$var parameter 8 <" i $end
$upscope $end
$scope begin rev[103] $end
$var parameter 8 =" i $end
$upscope $end
$upscope $end
$scope task test_tuple $end
$var reg 104 >" din [103:0] $end
$upscope $end
$upscope $end
$enddefinitions $end
$comment Show the parameter values. $end
$dumpall
b1100111 ="
b1100110 <"
b1100101 ;"
b1100100 :"
b1100011 9"
b1100010 8"
b1100001 7"
b1100000 6"
b1011111 5"
b1011110 4"
b1011101 3"
b1011100 2"
b1011011 1"
b1011010 0"
b1011001 /"
b1011000 ."
b1010111 -"
b1010110 ,"
b1010101 +"
b1010100 *"
b1010011 )"
b1010010 ("
b1010001 '"
b1010000 &"
b1001111 %"
b1001110 $"
b1001101 #"
b1001100 ""
b1001011 !"
b1001010 ~
b1001001 }
b1001000 |
b1000111 {
b1000110 z
b1000101 y
b1000100 x
b1000011 w
b1000010 v
b1000001 u
b1000000 t
b111111 s
b111110 r
b111101 q
b111100 p
b111011 o
b111010 n
b111001 m
b111000 l
b110111 k
b110110 j
b110101 i
b110100 h
b110011 g
b110010 f
b110001 e
b110000 d
b101111 c
b101110 b
b101101 a
b101100 `
b101011 _
b101010 ^
b101001 ]
b101000 \
b100111 [
b100110 Z
b100101 Y
b100100 X
b100011 W
b100010 V
b100001 U
b100000 T
b11111 S
b11110 R
b11101 Q
b11100 P
b11011 O
b11010 N
b11001 M
b11000 L
b10111 K
b10110 J
b10101 I
b10100 H
b10011 G
b10010 F
b10001 E
b10000 D
b1111 C
b1110 B
b1101 A
b1100 @
b1011 ?
b1010 >
b1001 =
b1000 <
b111 ;
b110 :
b101 9
b100 8
b11 7
b10 6
b1 5
b0 4
$end
#0
$dumpvars
bx >"
bx 3
bx 2
bx 1
bx 0
b0 /
b0 .
b100001101111 -
b100111110111 ,
b10100000000 +
b101000000000 *
0)
b0 (
1'
0&
bx %
bx $
bx #
bx "
x!
$end
#3200
0!
b0 "
b0 3
b0 #
b0 2
b0 $
b0 1
b0 %
b0 0
1&
#6400
0&
#9600
1&
#12800
0&
#16000
1&
#19200
0&
#22400
1&
#25600
0&
#28800
1&
#32000
0&
#35200
1&
#38400
0&
#41600
1&
#44800
0&
#48000
1&
#51200
0&
#54400
1&
#57600
0&
#60800
1&
#64000
0&
#67200
1&
#70400
0&
#73600
1&
#76800
0&
#80000
1&
#83200
0&
#86400
1&
#89600
0&
#92800
1&
#96000
0&
#99200
1&
#100000
0'
#102400
0&
#105600
1&
#108800
0&
#112000
1&
#115200
0&
#118400
1&
#120000
b0 >"
#121600
0&
#124800
1)
1&
#128000
0&
#131200
0)
b100001101111 "
b100001101111 3
b100111110111 #
b100111110111 2
b10100000000 $
b10100000000 1
b101000000000 %
b101000000000 0
1!
1&
#134400
0&
#137600
0!
1&
#140800
0&
#144000
b1000000100000001100000100000001010000011000000111000010000000100100001010000010110000110000001101 >"
1&
#147200
0&
#150400
b101001100101 -
b101110011000 ,
b10110100010 +
b101001000101 *
b10110000001100001101000001010000100100000001000011100000011000001010000000100000110000000100000010000000 /
b1000000100000001100000100000001010000011000000111000010000000100100001010000010110000110000001101 (
b1000000100000001100000100000001010000011000000111000010000000100100001010000010110000110000001101 .
1)
1&
#153600
0&
#156800
0)
b101001100101 "
b101001100101 3
b101110011000 #
b101110011000 2
b10110100010 $
b10110100010 1
b101001000101 %
b101001000101 0
1!
1&
#160000
0&
#163200
0!
1&
#166400
0&
#169600
b11000000101010000000000100000001000010100000000000000000000000010000010011010010000000000101000000010001 >"
1&
#172800
0&
#176000
b111111111000 -
b111100000001 ,
b101011101100 +
b10100110111 *
b10001000000010100000000001001011001000001000000000000000000000000101000010000000100000000001010100000011 /
b11000000101010000000000100000001000010100000000000000000000000010000010011010010000000000101000000010001 (
b11000000101010000000000100000001000010100000000000000000000000010000010011010010000000000101000000010001 .
1)
1&
#179200
0&
#182400
0)
b111111111000 "
b111111111000 3
b111100000001 #
b111100000001 2
b101011101100 $
b101011101100 1
b10100110111 %
b10100110111 0
1!
1&
#185600
0&
#188800
0!
1&
#192000
0&
#195200
b11000000101010000000000100000001000010100000000000000000000000010000010011010010000000000101000100010001 >"
1&
#198400
0&
#201600
b11000001001 ,
b10000110111 *
b10111111000 -
b1011101100 +
b10001000100010100000000001001011001000001000000000000000000000000101000010000000100000000001010100000011 /
b11000000101010000000000100000001000010100000000000000000000000010000010011010010000000000101000100010001 (
b11000000101010000000000100000001000010100000000000000000000000010000010011010010000000000101000100010001 .
1)
1&
#204800
0&
#208000
0)
b10111111000 "
b10111111000 3
b11000001001 #
b11000001001 2
b1011101100 $
b1011101100 1
b10000110111 %
b10000110111 0
1!
1&
#211200
0&
#214400
0!
1&
